flask_simple_deploy/__init__.py
flask_simple_deploy/cli.py
flask_simple_deploy/deploy.py
flask_simple_deploy/fsd_messages.py
flask_simple_deploy/hookspecs.py
flask_simple_deploy/plugins.py
flask_simple_deploy/utils/__init__.py
flask_simple_deploy/utils/command_errors.py
flask_simple_deploy/utils/fsd_config.py
flask_simple_deploy/utils/fsd_utils.py
flask_simple_deploy/utils/plugin_utils.py
flask_simple_deploy-0.0.1.dist-info/METADATA
flask_simple_deploy-0.0.1.dist-info/WHEEL
flask_simple_deploy-0.0.1.dist-info/entry_points.txt
flask_simple_deploy-0.0.1.dist-info/top_level.txt
flask_simple_deploy-0.0.1.dist-info/RECORD
